simple_logger/__init__.py
simple_logger/context.py
simple_logger/middleware.py
pyotel-0.1.2.dist-info/METADATA
pyotel-0.1.2.dist-info/WHEEL
pyotel-0.1.2.dist-info/top_level.txt
pyotel-0.1.2.dist-info/RECORD
