Metadata-Version: 2.4
Name: pyotel
Version: 0.1.2
Summary: A simple request/response logger with trace ID propagation for FastAPI
Author: ADv8
Author-email: adwaitg02@gmail.com
Classifier: Development Status :: 3 - Alpha
Classifier: Intended Audience :: Developers
Classifier: License :: OSI Approved :: MIT License
Classifier: Programming Language :: Python :: 3
Classifier: Programming Language :: Python :: 3.7
Classifier: Programming Language :: Python :: 3.8
Classifier: Programming Language :: Python :: 3.9
Classifier: Programming Language :: Python :: 3.10
Requires-Python: >=3.7
Requires-Dist: fastapi>=0.68.0
Requires-Dist: starlette>=0.14.2
Requires-Dist: aiohttp
Requires-Dist: requests
Dynamic: author
Dynamic: author-email
Dynamic: classifier
Dynamic: requires-dist
Dynamic: requires-python
Dynamic: summary
